{"name":"Login","id":"reservations;login","testSteps":[{"number":1,"description":"Example: null","duration":16602,"startTime":"2021-09-27T09:29:05.541-05:00[America/Bogota]","screenshots":[{"screenshot":"ad12d50677b5669cfc68ff6ef352412d48e2d1847ca1a051400a5d55bb3dd94d.png","timeStamp":1632752962143}],"result":"SUCCESS","precondition":false,"level":0,"lineNumber":25,"children":[{"number":2,"description":"Given the user Antonio is in the home page","duration":4352,"startTime":"2021-09-27T09:29:05.556-05:00[America/Bogota]","screenshots":[{"screenshot":"4e65fce13b5e7e3984cab02484af4211555106e939e20ce54ed71a62d45a4727.png","timeStamp":1632752949908}],"result":"SUCCESS","precondition":false,"level":1,"children":[{"number":3,"description":"Antonio opens the Home page","duration":4325,"startTime":"2021-09-27T09:29:05.577-05:00[America/Bogota]","screenshots":[{"screenshot":"4e65fce13b5e7e3984cab02484af4211555106e939e20ce54ed71a62d45a4727.png","timeStamp":1632752949902}],"result":"SUCCESS","precondition":false,"level":2}]},{"number":4,"description":"When the user looks for option Front-End Home Page","duration":484,"startTime":"2021-09-27T09:29:09.912-05:00[America/Bogota]","screenshots":[{"screenshot":"8d8850315ae69e8d2f7bcd0c3d759e0414f451068a6598751433aa98bc54d56a.png","timeStamp":1632752950396}],"result":"SUCCESS","precondition":false,"level":1,"children":[{"number":5,"description":"Antonio looks task","duration":449,"startTime":"2021-09-27T09:29:09.942-05:00[America/Bogota]","screenshots":[{"screenshot":"8d8850315ae69e8d2f7bcd0c3d759e0414f451068a6598751433aa98bc54d56a.png","timeStamp":1632752950391}],"result":"SUCCESS","precondition":false,"level":2}]},{"number":6,"description":"And the user enters the Front-End Home Page https://www.phptravels.net/","duration":5895,"startTime":"2021-09-27T09:29:10.399-05:00[America/Bogota]","screenshots":[{"screenshot":"6a6c9ab98420996122e086acea5bbf5d6af5be99d18a70761ef9e3b9fb0c77cf.png","timeStamp":1632752956294}],"result":"SUCCESS","precondition":false,"level":1,"children":[{"number":7,"description":"Antonio front end page task","duration":4885,"startTime":"2021-09-27T09:29:10.422-05:00[America/Bogota]","screenshots":[{"screenshot":"5b7f2b7c7e2f6cfb6d1978c9c0e0b00b9a8a4b85c3d81a0421ab5b80cafae5d5.png","timeStamp":1632752955306}],"result":"SUCCESS","precondition":false,"level":2,"children":[{"number":8,"description":"Antonio clicks on Homepage Front-End","duration":685,"startTime":"2021-09-27T09:29:10.441-05:00[America/Bogota]","screenshots":[{"screenshot":"8634e1b00806154df8f56ac87f76e7289a6f7185c92a9573e1338046b6ef4715.png","timeStamp":1632752951126}],"result":"SUCCESS","precondition":false,"level":3}]},{"number":9,"description":"Then question url f end","duration":977,"startTime":"2021-09-27T09:29:15.313-05:00[America/Bogota]","screenshots":[{"screenshot":"6a6c9ab98420996122e086acea5bbf5d6af5be99d18a70761ef9e3b9fb0c77cf.png","timeStamp":1632752956290}],"result":"SUCCESS","precondition":false,"level":2,"children":[{"number":10,"description":"Antonio clicks on Cookies","duration":837,"startTime":"2021-09-27T09:29:15.437-05:00[America/Bogota]","screenshots":[{"screenshot":"6a6c9ab98420996122e086acea5bbf5d6af5be99d18a70761ef9e3b9fb0c77cf.png","timeStamp":1632752956273}],"result":"SUCCESS","precondition":false,"level":3}]}]},{"number":11,"description":"And the user enters credentials and logs in","duration":5495,"startTime":"2021-09-27T09:29:16.299-05:00[America/Bogota]","screenshots":[{"screenshot":"b8b9d987bdc978617ee76aea9ae571667ef0fff400a4ca8b291d4c5d895f058f.png","timeStamp":1632752961794}],"result":"SUCCESS","precondition":false,"level":1,"children":[{"number":12,"description":"Antonio login task","duration":5457,"startTime":"2021-09-27T09:29:16.327-05:00[America/Bogota]","screenshots":[{"screenshot":"b8b9d987bdc978617ee76aea9ae571667ef0fff400a4ca8b291d4c5d895f058f.png","timeStamp":1632752961784}],"result":"SUCCESS","precondition":false,"level":2,"children":[{"number":13,"description":"Antonio clicks on Option Login","duration":1284,"startTime":"2021-09-27T09:29:16.420-05:00[America/Bogota]","screenshots":[{"screenshot":"9c0b0a3e6177793b05cb02459e1bcbc543481a27e43443313e52915878d4e499.png","timeStamp":1632752957704}],"result":"SUCCESS","precondition":false,"level":3},{"number":14,"description":"Antonio enters \u0027user@phptravels.com\u0027 into input email","duration":788,"startTime":"2021-09-27T09:29:17.707-05:00[America/Bogota]","screenshots":[{"screenshot":"85e1dd0c28fd0c499b8e725c8a91003e07639432b1b89f2815ba5109875801e2.png","timeStamp":1632752958495}],"result":"SUCCESS","precondition":false,"level":3},{"number":15,"description":"Antonio enters \u0027demouser\u0027 into input password","duration":518,"startTime":"2021-09-27T09:29:18.498-05:00[America/Bogota]","screenshots":[{"screenshot":"6a5158fb99ab6fc40fd2dc3e4b04ab698945acfe55d683d7e0567455c2b5caf3.png","timeStamp":1632752959015}],"result":"SUCCESS","precondition":false,"level":3},{"number":16,"description":"Antonio clicks on Button Login","duration":2762,"startTime":"2021-09-27T09:29:19.018-05:00[America/Bogota]","screenshots":[{"screenshot":"b8b9d987bdc978617ee76aea9ae571667ef0fff400a4ca8b291d4c5d895f058f.png","timeStamp":1632752961780}],"result":"SUCCESS","precondition":false,"level":3}]}]},{"number":17,"description":"Then the user validates that the username Demo on the user home page","duration":339,"startTime":"2021-09-27T09:29:21.799-05:00[America/Bogota]","screenshots":[{"screenshot":"ad12d50677b5669cfc68ff6ef352412d48e2d1847ca1a051400a5d55bb3dd94d.png","timeStamp":1632752962138}],"result":"SUCCESS","precondition":false,"level":1,"children":[{"number":18,"description":"Then question username","duration":326,"startTime":"2021-09-27T09:29:21.808-05:00[America/Bogota]","screenshots":[{"screenshot":"ad12d50677b5669cfc68ff6ef352412d48e2d1847ca1a051400a5d55bb3dd94d.png","timeStamp":1632752962134}],"result":"SUCCESS","precondition":false,"level":2}]}]}],"userStory":{"id":"reservations","storyName":"Reservations","path":"src/test/resources/features/Bookings.feature","type":"feature"},"featureTag":{"name":"Features/Reservations","type":"feature","displayName":"Features/Reservations"},"title":"Login","tags":[{"name":"tag2","type":"tag","displayName":"tag2"},{"name":"tag","type":"tag","displayName":"tag"},{"name":"Reservations","type":"feature","displayName":"Reservations"}],"startTime":"2021-09-27T09:29:05.524-05:00[America/Bogota]","duration":17727,"projectKey":"","driver":"chrome:antonio","isManualTestingUpToDate":false,"manual":false,"testSource":"Cucumber","actors":[{"name":"Antonio","can":["browse the web"]}],"result":"SUCCESS","scenarioOutline":"Given the user \u003cvclient\u003e is in the home page\r\nWhen the user looks for option Front-End Home Page\r\nAnd the user enters the Front-End Home Page \u003cfendpage\u003e\r\nAnd the user enters credentials and logs in\r\nThen the user validates that the username \u003cusername\u003e on the user home page"}